<?xml version="1.0" encoding="utf-8"?>
<transfers xmlns="transfer-schema"
           xmlns:xsi="http://www.w3.org/2001/XMLSchema-instance"
           xsi:schemaLocation="transfer-schema ../../../Transfer/Templates/schema.xsd">

    <transfer name="LongTermParker">
        <property name="id" type="int"/>
        <property name="firstName" type="string"/>
        <property name="lastName" type="string"/>
    </transfer>

    <transfer name="Parker">
        <property name="id" type="int"/>
        <property name="licencePlate" type="string"/>
        <property name="longTermParkerId" type="int"/>
    </transfer>
</transfers>
